xj_captcha/__init__.py
xj_captcha/apps.py
xj_captcha/common.py
xj_captcha/models.py
xj_captcha/service_register.py
xj_captcha/urls.py
xj_captcha/apis/SmsApis.py
xj_captcha/apis/__init__.py
xj_captcha/apis/send_short_message.py
xj_captcha/services/__init__.py
xj_captcha/services/send_short_message_service.py
xj_captcha/services/sms_service.py
xj_captcha/utils/__init__.py
xj_captcha/utils/common.py
xj_captcha/utils/custom_response.py
xj_captcha/utils/custom_tool.py
xj_captcha/utils/j_config.py
xj_captcha/utils/j_dict.py
xj_captcha/utils/model_handle.py
xj_captcha/utils/user_wrapper.py
xj_captcha/utils/utility_method.py
xj_captcha/utils/utils.py
xj_captcha-1.0.15.dist-info/METADATA
xj_captcha-1.0.15.dist-info/WHEEL
xj_captcha-1.0.15.dist-info/top_level.txt
xj_captcha-1.0.15.dist-info/RECORD
