Metadata-Version: 2.1
Name: xj-captcha
Version: 1.0.15
Summary: 短信模块
License: apache 3.0
Requires-Dist: python-alipay-sdk (>=3.1.0)
Requires-Dist: aliyun-python-sdk-core (>=2.13.36)
Requires-Dist: qcloudsms-py (>=0.1.4)
